glassio/__init__.py
glassio/command.py
glassio/config.py
glassio/context.py
glassio/errors.py
glassio/types.py
glassio/util.py
glassio/cache/__init__.py
glassio/cache/abc.py
glassio/cache/memcached.py
glassio/cache/no_cache.py
glassio/cache/simple.py
glassio/commands/__init__.py
glassio/commands/init.py
glassio/taskq/__init__.py
glassio/taskq/base_queue.py
glassio/taskq/errors.py
glassio/taskq/mongo_queue.py
glassio/taskq/task.py
glassio/taskq/types.py
glassio/taskq/worker.py
glassio/templates/.shellrc.py
glassio/templates/development.toml
glassio/templates/glass.py
glassio/templates/app/__init__.py
glassio/templates/app/app.py
glassio/templates/app/extractors.py
glassio/templates/app/middleware.py
glassio/templates/app/controllers/__init__.py
glassio/templates/app/controllers/api/__init__.py
glassio/templates/app/controllers/api/v1/__init__.py
glassio/templates/app/controllers/api/v1/account.py
glassio/templates/app/controllers/api/v1/response_types/__init__.py
glassio/templates/app/controllers/api/v1/response_types/account.py
glassio/templates/app/models/__init__.py
glassio/templates/app/models/session.py
glassio/templates/app/models/token.py
glassio/templates/app/models/user.py
glassio/tests/__init__.py
glassio/tests/test_base_model.py
glassio/uorm/__init__.py
glassio/uorm/db.py
glassio/uorm/decorators.py
glassio/uorm/errors.py
glassio/uorm/util.py
glassio/uorm/models/__init__.py
glassio/uorm/models/base_model.py
glassio/uorm/models/counter.py
glassio/uorm/models/fields.py
glassio/uorm/models/index.py
glassio/uorm/models/meta_model.py
glassio/uorm/models/storable_model.py
glassio-0.4.1.dist-info/METADATA
glassio-0.4.1.dist-info/WHEEL
glassio-0.4.1.dist-info/entry_points.txt
glassio-0.4.1.dist-info/top_level.txt
glassio-0.4.1.dist-info/RECORD
