Metadata-Version: 2.1
Name: glassio
Version: 0.4.1
Summary: a micro webframework based on fastapi and motor
Home-page: https://gitlab.com/viert/glassio
Author: Pavel Vorobyev
Author-email: aquavitale@yandex.ru
License: MIT
Requires-Python: >=3.11
Requires-Dist: fastapi[all]
Requires-Dist: uvicorn
Requires-Dist: pymongo
Requires-Dist: motor
Requires-Dist: pydantic
Requires-Dist: ipython
Requires-Dist: requests
Requires-Dist: bcrypt
